pipsearchguitk.py
pipsearchguitk-0.1.1.dist-info/LICENSE.txt
pipsearchguitk-0.1.1.dist-info/METADATA
pipsearchguitk-0.1.1.dist-info/WHEEL
pipsearchguitk-0.1.1.dist-info/top_level.txt
pipsearchguitk-0.1.1.dist-info/RECORD
